{
    "traceEvents": [
        {
            "pid": 0,
            "name": "process_name",
            "args": {
                "name": "Allocators"
            },
            "ph": "M"
        },
        {
            "pid": 1,
            "name": "process_name",
            "args": {
                "name": "/job:localhost/replica:0/task:0/device:CPU:0 Compute"
            },
            "ph": "M"
        },
        {
            "pid": 2,
            "name": "process_name",
            "args": {
                "name": "/job:localhost/replica:0/task:0/device:CPU:0 Tensors"
            },
            "ph": "M"
        },
        {
            "pid": 1,
            "dur": 12,
            "name": "NoOp",
            "ph": "X",
            "args": {
                "op": "NoOp",
                "name": "_SOURCE"
            },
            "ts": 1554448472992419,
            "cat": "Op",
            "tid": 0
        },
        {
            "pid": 1,
            "dur": 17,
            "name": "VariableV2",
            "ph": "X",
            "args": {
                "op": "VariableV2",
                "name": "conv5/biases"
            },
            "ts": 1554448472992496,
            "cat": "Op",
            "tid": 0
        },
        {
            "pid": 1,
            "dur": 2,
            "name": "Identity",
            "ph": "X",
            "args": {
                "op": "Identity",
                "input0": "conv5/biases",
                "name": "conv5/biases/read"
            },
            "ts": 1554448472992517,
            "cat": "Op",
            "tid": 0
        },
        {
            "pid": 1,
            "dur": 13,
            "name": "VariableV2",
            "ph": "X",
            "args": {
                "op": "VariableV2",
                "name": "conv5/weights"
            },
            "ts": 1554448472992507,
            "cat": "Op",
            "tid": 1
        },
        {
            "pid": 1,
            "dur": 13,
            "name": "VariableV2",
            "ph": "X",
            "args": {
                "op": "VariableV2",
                "name": "conv4/weights"
            },
            "ts": 1554448472992508,
            "cat": "Op",
            "tid": 2
        },
        {
            "pid": 1,
            "dur": 9,
            "name": "Identity",
            "ph": "X",
            "args": {
                "op": "Identity",
                "input0": "conv5/weights",
                "name": "conv5/weights/read"
            },
            "ts": 1554448472992523,
            "cat": "Op",
            "tid": 0
        },
        {
            "pid": 1,
            "name": "conv5/weights",
            "ph": "s",
            "ts": 1554448472992520,
            "cat": "DataFlow",
            "tid": 1,
            "id": 0
        },
        {
            "pid": 1,
            "name": "conv5/weights",
            "ph": "t",
            "ts": 1554448472992523,
            "cat": "DataFlow",
            "tid": 0,
            "id": 0
        },
        {
            "pid": 1,
            "dur": 12,
            "name": "VariableV2",
            "ph": "X",
            "args": {
                "op": "VariableV2",
                "name": "conv2/biases"
            },
            "ts": 1554448472992521,
            "cat": "Op",
            "tid": 1
        },
        {
            "pid": 1,
            "dur": 13,
            "name": "VariableV2",
            "ph": "X",
            "args": {
                "op": "VariableV2",
                "name": "conv3/weights"
            },
            "ts": 1554448472992520,
            "cat": "Op",
            "tid": 3
        },
        {
            "pid": 1,
            "dur": 2,
            "name": "Identity",
            "ph": "X",
            "args": {
                "op": "Identity",
                "input0": "conv2/biases",
                "name": "conv2/biases/read"
            },
            "ts": 1554448472992534,
            "cat": "Op",
            "tid": 0
        },
        {
            "pid": 1,
            "name": "conv2/biases",
            "ph": "s",
            "ts": 1554448472992533,
            "cat": "DataFlow",
            "tid": 1,
            "id": 1
        },
        {
            "pid": 1,
            "name": "conv2/biases",
            "ph": "t",
            "ts": 1554448472992534,
            "cat": "DataFlow",
            "tid": 0,
            "id": 1
        },
        {
            "pid": 1,
            "dur": 3,
            "name": "VariableV2",
            "ph": "X",
            "args": {
                "op": "VariableV2",
                "name": "conv1/weights"
            },
            "ts": 1554448472992535,
            "cat": "Op",
            "tid": 1
        },
        {
            "pid": 1,
            "dur": 7,
            "name": "Const",
            "ph": "X",
            "args": {
                "op": "Const",
                "name": "gradients/Reshape_grad/Shape"
            },
            "ts": 1554448472992532,
            "cat": "Op",
            "tid": 2
        },
        {
            "pid": 1,
            "dur": 1,
            "name": "Identity",
            "ph": "X",
            "args": {
                "op": "Identity",
                "input0": "conv1/weights",
                "name": "conv1/weights/read"
            },
            "ts": 1554448472992540,
            "cat": "Op",
            "tid": 0
        },
        {
            "pid": 1,
            "name": "conv1/weights",
            "ph": "s",
            "ts": 1554448472992538,
            "cat": "DataFlow",
            "tid": 1,
            "id": 2
        },
        {
            "pid": 1,
            "name": "conv1/weights",
            "ph": "t",
            "ts": 1554448472992540,
            "cat": "DataFlow",
            "tid": 0,
            "id": 2
        },
        {
            "pid": 1,
            "dur": 4,
            "name": "VariableV2",
            "ph": "X",
            "args": {
                "op": "VariableV2",
                "name": "weight6"
            },
            "ts": 1554448472992538,
            "cat": "Op",
            "tid": 3
        },
        {
            "pid": 1,
            "dur": 4,
            "name": "Identity",
            "ph": "X",
            "args": {
                "op": "Identity",
                "input0": "conv4/weights",
                "name": "conv4/weights/read"
            },
            "ts": 1554448472992539,
            "cat": "Op",
            "tid": 1
        },
        {
            "pid": 1,
            "name": "conv4/weights",
            "ph": "s",
            "ts": 1554448472992521,
            "cat": "DataFlow",
            "tid": 2,
            "id": 3
        },
        {
            "pid": 1,
            "name": "conv4/weights",
            "ph": "t",
            "ts": 1554448472992539,
            "cat": "DataFlow",
            "tid": 1,
            "id": 3
        },
        {
            "pid": 1,
            "dur": 3,
            "name": "Const",
            "ph": "X",
            "args": {
                "op": "Const",
                "name": "Reshape/shape"
            },
            "ts": 1554448472992541,
            "cat": "Op",
            "tid": 2
        },
        {
            "pid": 1,
            "dur": 22,
            "name": "VariableV2",
            "ph": "X",
            "args": {
                "op": "VariableV2",
                "name": "conv3/biases"
            },
            "ts": 1554448472992519,
            "cat": "Op",
            "tid": 4
        },
        {
            "pid": 1,
            "dur": 2,
            "name": "Identity",
            "ph": "X",
            "args": {
                "op": "Identity",
                "input0": "weight6",
                "name": "weight6/read"
            },
            "ts": 1554448472992543,
            "cat": "Op",
            "tid": 0
        },
        {
            "pid": 1,
            "name": "weight6",
            "ph": "s",
            "ts": 1554448472992542,
            "cat": "DataFlow",
            "tid": 3,
            "id": 4
        },
        {
            "pid": 1,
            "name": "weight6",
            "ph": "t",
            "ts": 1554448472992543,
            "cat": "DataFlow",
            "tid": 0,
            "id": 4
        },
        {
            "pid": 1,
            "dur": 5,
            "name": "VariableV2",
            "ph": "X",
            "args": {
                "op": "VariableV2",
                "name": "ful_bias1"
            },
            "ts": 1554448472992541,
            "cat": "Op",
            "tid": 5
        },
        {
            "pid": 1,
            "dur": 20,
            "name": "VariableV2",
            "ph": "X",
            "args": {
                "op": "VariableV2",
                "name": "conv2/weights"
            },
            "ts": 1554448472992529,
            "cat": "Op",
            "tid": 6
        },
        {
            "pid": 1,
            "dur": 5,
            "name": "VariableV2",
            "ph": "X",
            "args": {
                "op": "VariableV2",
                "name": "weight9"
            },
            "ts": 1554448472992548,
            "cat": "Op",
            "tid": 0
        },
        {
            "pid": 1,
            "dur": 6,
            "name": "Identity",
            "ph": "X",
            "args": {
                "op": "Identity",
                "input0": "conv3/biases",
                "name": "conv3/biases/read"
            },
            "ts": 1554448472992547,
            "cat": "Op",
            "tid": 1
        },
        {
            "pid": 1,
            "name": "conv3/biases",
            "ph": "s",
            "ts": 1554448472992541,
            "cat": "DataFlow",
            "tid": 4,
            "id": 5
        },
        {
            "pid": 1,
            "name": "conv3/biases",
            "ph": "t",
            "ts": 1554448472992547,
            "cat": "DataFlow",
            "tid": 1,
            "id": 5
        },
        {
            "pid": 1,
            "dur": 14,
            "name": "VariableV2",
            "ph": "X",
            "args": {
                "op": "VariableV2",
                "name": "conv4/biases"
            },
            "ts": 1554448472992507,
            "cat": "Op",
            "tid": 7
        },
        {
            "pid": 1,
            "dur": 2,
            "name": "Identity",
            "ph": "X",
            "args": {
                "op": "Identity",
                "input0": "weight9",
                "name": "weight9/read"
            },
            "ts": 1554448472992554,
            "cat": "Op",
            "tid": 0
        },
        {
            "pid": 1,
            "dur": 16,
            "name": "VariableV2",
            "ph": "X",
            "args": {
                "op": "VariableV2",
                "name": "Variable"
            },
            "ts": 1554448472992541,
            "cat": "Op",
            "tid": 7
        },
        {
            "pid": 1,
            "dur": 5,
            "name": "Identity",
            "ph": "X",
            "args": {
                "op": "Identity",
                "input0": "conv2/weights",
                "name": "conv2/weights/read"
            },
            "ts": 1554448472992554,
            "cat": "Op",
            "tid": 1
        },
        {
            "pid": 1,
            "name": "conv2/weights",
            "ph": "s",
            "ts": 1554448472992549,
            "cat": "DataFlow",
            "tid": 6,
            "id": 6
        },
        {
            "pid": 1,
            "name": "conv2/weights",
            "ph": "t",
            "ts": 1554448472992554,
            "cat": "DataFlow",
            "tid": 1,
            "id": 6
        },
        {
            "pid": 1,
            "dur": 3,
            "name": "Identity",
            "ph": "X",
            "args": {
                "op": "Identity",
                "input0": "ful_bias1",
                "name": "ful_bias1/read"
            },
            "ts": 1554448472992548,
            "cat": "Op",
            "tid": 2
        },
        {
            "pid": 1,
            "name": "ful_bias1",
            "ph": "s",
            "ts": 1554448472992546,
            "cat": "DataFlow",
            "tid": 5,
            "id": 7
        },
        {
            "pid": 1,
            "name": "ful_bias1",
            "ph": "t",
            "ts": 1554448472992548,
            "cat": "DataFlow",
            "tid": 2,
            "id": 7
        },
        {
            "pid": 1,
            "dur": 2,
            "name": "Const",
            "ph": "X",
            "args": {
                "op": "Const",
                "name": "gradients/Softmax_grad/Sum/reduction_indices"
            },
            "ts": 1554448472992545,
            "cat": "Op",
            "tid": 3
        },
        {
            "pid": 1,
            "dur": 4,
            "name": "Identity",
            "ph": "X",
            "args": {
                "op": "Identity",
                "input0": "Variable",
                "name": "Variable/read"
            },
            "ts": 1554448472992561,
            "cat": "Op",
            "tid": 0
        },
        {
            "pid": 1,
            "name": "Variable",
            "ph": "s",
            "ts": 1554448472992557,
            "cat": "DataFlow",
            "tid": 7,
            "id": 8
        },
        {
            "pid": 1,
            "name": "Variable",
            "ph": "t",
            "ts": 1554448472992561,
            "cat": "DataFlow",
            "tid": 0,
            "id": 8
        },
        {
            "pid": 1,
            "dur": 3,
            "name": "Identity",
            "ph": "X",
            "args": {
                "op": "Identity",
                "input0": "conv3/weights",
                "name": "conv3/weights/read"
            },
            "ts": 1554448472992543,
            "cat": "Op",
            "tid": 4
        },
        {
            "pid": 1,
            "name": "conv3/weights",
            "ph": "s",
            "ts": 1554448472992533,
            "cat": "DataFlow",
            "tid": 3,
            "id": 9
        },
        {
            "pid": 1,
            "name": "conv3/weights",
            "ph": "t",
            "ts": 1554448472992543,
            "cat": "DataFlow",
            "tid": 4,
            "id": 9
        },
        {
            "pid": 1,
            "dur": 7,
            "name": "VariableV2",
            "ph": "X",
            "args": {
                "op": "VariableV2",
                "name": "ful_bias3"
            },
            "ts": 1554448472992545,
            "cat": "Op",
            "tid": 8
        },
        {
            "pid": 1,
            "dur": 21,
            "name": "VariableV2",
            "ph": "X",
            "args": {
                "op": "VariableV2",
                "name": "weight7"
            },
            "ts": 1554448472992548,
            "cat": "Op",
            "tid": 3
        },
        {
            "pid": 1,
            "dur": 6,
            "name": "VariableV2",
            "ph": "X",
            "args": {
                "op": "VariableV2",
                "name": "bias9"
            },
            "ts": 1554448472992566,
            "cat": "Op",
            "tid": 0
        },
        {
            "pid": 1,
            "dur": 23,
            "name": "VariableV2",
            "ph": "X",
            "args": {
                "op": "VariableV2",
                "name": "weight8"
            },
            "ts": 1554448472992550,
            "cat": "Op",
            "tid": 4
        },
        {
            "pid": 1,
            "dur": 37,
            "name": "VariableV2",
            "ph": "X",
            "args": {
                "op": "VariableV2",
                "name": "ful_bias2"
            },
            "ts": 1554448472992543,
            "cat": "Op",
            "tid": 9
        },
        {
            "pid": 1,
            "dur": 2,
            "name": "Identity",
            "ph": "X",
            "args": {
                "op": "Identity",
                "input0": "ful_bias3",
                "name": "ful_bias3/read"
            },
            "ts": 1554448472992570,
            "cat": "Op",
            "tid": 1
        },
        {
            "pid": 1,
            "name": "ful_bias3",
            "ph": "s",
            "ts": 1554448472992552,
            "cat": "DataFlow",
            "tid": 8,
            "id": 10
        },
        {
            "pid": 1,
            "name": "ful_bias3",
            "ph": "t",
            "ts": 1554448472992570,
            "cat": "DataFlow",
            "tid": 1,
            "id": 10
        },
        {
            "pid": 1,
            "dur": 3,
            "name": "Identity",
            "ph": "X",
            "args": {
                "op": "Identity",
                "input0": "ful_bias2",
                "name": "ful_bias2/read"
            },
            "ts": 1554448472992581,
            "cat": "Op",
            "tid": 0
        },
        {
            "pid": 1,
            "name": "ful_bias2",
            "ph": "s",
            "ts": 1554448472992580,
            "cat": "DataFlow",
            "tid": 9,
            "id": 11
        },
        {
            "pid": 1,
            "name": "ful_bias2",
            "ph": "t",
            "ts": 1554448472992581,
            "cat": "DataFlow",
            "tid": 0,
            "id": 11
        },
        {
            "pid": 1,
            "dur": 5,
            "name": "Identity",
            "ph": "X",
            "args": {
                "op": "Identity",
                "input0": "weight8",
                "name": "weight8/read"
            },
            "ts": 1554448472992581,
            "cat": "Op",
            "tid": 1
        },
        {
            "pid": 1,
            "name": "weight8",
            "ph": "s",
            "ts": 1554448472992573,
            "cat": "DataFlow",
            "tid": 4,
            "id": 12
        },
        {
            "pid": 1,
            "name": "weight8",
            "ph": "t",
            "ts": 1554448472992581,
            "cat": "DataFlow",
            "tid": 1,
            "id": 12
        },
        {
            "pid": 1,
            "dur": 3,
            "name": "Const",
            "ph": "X",
            "args": {
                "op": "Const",
                "input0": "^conv1/weights/read",
                "name": "ConstantFolding/gradients/conv1/Conv2D_grad/ShapeN-matshapes-1",
                "input1": "^Variable/read"
            },
            "ts": 1554448472992596,
            "cat": "Op",
            "tid": 0
        },
        {
            "pid": 1,
            "dur": 49,
            "name": "Identity",
            "ph": "X",
            "args": {
                "op": "Identity",
                "input0": "conv4/biases",
                "name": "conv4/biases/read"
            },
            "ts": 1554448472992561,
            "cat": "Op",
            "tid": 2
        },
        {
            "pid": 1,
            "name": "conv4/biases",
            "ph": "s",
            "ts": 1554448472992521,
            "cat": "DataFlow",
            "tid": 7,
            "id": 13
        },
        {
            "pid": 1,
            "name": "conv4/biases",
            "ph": "t",
            "ts": 1554448472992561,
            "cat": "DataFlow",
            "tid": 2,
            "id": 13
        },
        {
            "pid": 1,
            "dur": 4,
            "name": "Identity",
            "ph": "X",
            "args": {
                "op": "Identity",
                "input0": "bias9",
                "name": "bias9/read"
            },
            "ts": 1554448472992583,
            "cat": "Op",
            "tid": 3
        },
        {
            "pid": 1,
            "name": "bias9",
            "ph": "s",
            "ts": 1554448472992572,
            "cat": "DataFlow",
            "tid": 0,
            "id": 14
        },
        {
            "pid": 1,
            "name": "bias9",
            "ph": "t",
            "ts": 1554448472992583,
            "cat": "DataFlow",
            "tid": 3,
            "id": 14
        },
        {
            "pid": 1,
            "dur": 21,
            "name": "VariableV2",
            "ph": "X",
            "args": {
                "op": "VariableV2",
                "name": "conv1/biases"
            },
            "ts": 1554448472992531,
            "cat": "Op",
            "tid": 10
        },
        {
            "pid": 1,
            "dur": 8,
            "name": "Identity",
            "ph": "X",
            "args": {
                "op": "Identity",
                "input0": "conv1/biases",
                "name": "conv1/biases/read"
            },
            "ts": 1554448472992628,
            "cat": "Op",
            "tid": 0
        },
        {
            "pid": 1,
            "name": "conv1/biases",
            "ph": "s",
            "ts": 1554448472992552,
            "cat": "DataFlow",
            "tid": 10,
            "id": 15
        },
        {
            "pid": 1,
            "name": "conv1/biases",
            "ph": "t",
            "ts": 1554448472992628,
            "cat": "DataFlow",
            "tid": 0,
            "id": 15
        },
        {
            "pid": 1,
            "dur": 40,
            "name": "Identity",
            "ph": "X",
            "args": {
                "op": "Identity",
                "input0": "weight7",
                "name": "weight7/read"
            },
            "ts": 1554448472992574,
            "cat": "Op",
            "tid": 4
        },
        {
            "pid": 1,
            "name": "weight7",
            "ph": "s",
            "ts": 1554448472992569,
            "cat": "DataFlow",
            "tid": 3,
            "id": 16
        },
        {
            "pid": 1,
            "name": "weight7",
            "ph": "t",
            "ts": 1554448472992574,
            "cat": "DataFlow",
            "tid": 4,
            "id": 16
        },
        {
            "pid": 1,
            "dur": 51118,
            "name": "_FusedConv2D",
            "ph": "X",
            "args": {
                "input2": "conv1/biases/read",
                "op": "_FusedConv2D",
                "input0": "Variable/read",
                "name": "conv1",
                "input1": "conv1/weights/read"
            },
            "ts": 1554448472992639,
            "cat": "Op",
            "tid": 0
        },
        {
            "pid": 1,
            "dur": 17076,
            "name": "LRN",
            "ph": "X",
            "args": {
                "op": "LRN",
                "input0": "conv1",
                "name": "conv1/lrn1"
            },
            "ts": 1554448473043785,
            "cat": "Op",
            "tid": 0
        },
        {
            "pid": 1,
            "dur": 5490,
            "name": "MaxPool",
            "ph": "X",
            "args": {
                "op": "MaxPool",
                "input0": "conv1/lrn1",
                "name": "conv1/pool1"
            },
            "ts": 1554448473060881,
            "cat": "Op",
            "tid": 0
        },
        {
            "pid": 1,
            "dur": 10,
            "name": "Const",
            "ph": "X",
            "args": {
                "op": "Const",
                "input0": "^conv2/weights/read",
                "name": "ConstantFolding/gradients/conv2/Conv2D_grad/ShapeN-matshapes-1",
                "input1": "^conv1/pool1"
            },
            "ts": 1554448473066398,
            "cat": "Op",
            "tid": 0
        },
        {
            "pid": 1,
            "dur": 3,
            "name": "Const",
            "ph": "X",
            "args": {
                "op": "Const",
                "input0": "^conv2/weights/read",
                "name": "ConstantFolding/gradients/conv2/Conv2D_grad/ShapeN-matshapes-0",
                "input1": "^conv1/pool1"
            },
            "ts": 1554448473066412,
            "cat": "Op",
            "tid": 0
        },
        {
            "pid": 1,
            "dur": 35416,
            "name": "_FusedConv2D",
            "ph": "X",
            "args": {
                "input2": "conv2/biases/read",
                "op": "_FusedConv2D",
                "input0": "conv1/pool1",
                "name": "conv2",
                "input1": "conv2/weights/read"
            },
            "ts": 1554448473066419,
            "cat": "Op",
            "tid": 0
        },
        {
            "pid": 1,
            "name": "conv2/weights/read",
            "ph": "s",
            "ts": 1554448472992559,
            "cat": "DataFlow",
            "tid": 1,
            "id": 17
        },
        {
            "pid": 1,
            "name": "conv2/weights/read",
            "ph": "t",
            "ts": 1554448473066419,
            "cat": "DataFlow",
            "tid": 0,
            "id": 17
        },
        {
            "pid": 1,
            "dur": 14425,
            "name": "LRN",
            "ph": "X",
            "args": {
                "op": "LRN",
                "input0": "conv2",
                "name": "conv2/lrn2"
            },
            "ts": 1554448473101862,
            "cat": "Op",
            "tid": 0
        },
        {
            "pid": 1,
            "dur": 891,
            "name": "MaxPool",
            "ph": "X",
            "args": {
                "op": "MaxPool",
                "input0": "conv2/lrn2",
                "name": "conv2/pool2"
            },
            "ts": 1554448473116299,
            "cat": "Op",
            "tid": 0
        },
        {
            "pid": 1,
            "dur": 9,
            "name": "Const",
            "ph": "X",
            "args": {
                "op": "Const",
                "input0": "^conv3/weights/read",
                "name": "ConstantFolding/gradients/conv3/Conv2D_grad/ShapeN-matshapes-1",
                "input1": "^conv2/pool2"
            },
            "ts": 1554448473117202,
            "cat": "Op",
            "tid": 0
        },
        {
            "pid": 1,
            "dur": 2,
            "name": "Const",
            "ph": "X",
            "args": {
                "op": "Const",
                "input0": "^conv3/weights/read",
                "name": "ConstantFolding/gradients/conv3/Conv2D_grad/ShapeN-matshapes-0",
                "input1": "^conv2/pool2"
            },
            "ts": 1554448473117215,
            "cat": "Op",
            "tid": 0
        },
        {
            "pid": 1,
            "dur": 24639,
            "name": "_FusedConv2D",
            "ph": "X",
            "args": {
                "input2": "conv3/biases/read",
                "op": "_FusedConv2D",
                "input0": "conv2/pool2",
                "name": "conv3",
                "input1": "conv3/weights/read"
            },
            "ts": 1554448473117221,
            "cat": "Op",
            "tid": 0
        },
        {
            "pid": 1,
            "name": "conv3/weights/read",
            "ph": "s",
            "ts": 1554448472992546,
            "cat": "DataFlow",
            "tid": 4,
            "id": 18
        },
        {
            "pid": 1,
            "name": "conv3/weights/read",
            "ph": "t",
            "ts": 1554448473117221,
            "cat": "DataFlow",
            "tid": 0,
            "id": 18
        },
        {
            "pid": 1,
            "name": "conv3/biases/read",
            "ph": "s",
            "ts": 1554448472992553,
            "cat": "DataFlow",
            "tid": 1,
            "id": 19
        },
        {
            "pid": 1,
            "name": "conv3/biases/read",
            "ph": "t",
            "ts": 1554448473117221,
            "cat": "DataFlow",
            "tid": 0,
            "id": 19
        },
        {
            "pid": 1,
            "dur": 8,
            "name": "Const",
            "ph": "X",
            "args": {
                "op": "Const",
                "input0": "^conv4/weights/read",
                "name": "ConstantFolding/gradients/conv4/Conv2D_grad/ShapeN-matshapes-1",
                "input1": "^conv3"
            },
            "ts": 1554448473141879,
            "cat": "Op",
            "tid": 0
        },
        {
            "pid": 1,
            "dur": 3,
            "name": "Const",
            "ph": "X",
            "args": {
                "op": "Const",
                "input0": "^conv4/weights/read",
                "name": "ConstantFolding/gradients/conv4/Conv2D_grad/ShapeN-matshapes-0",
                "input1": "^conv3"
            },
            "ts": 1554448473141892,
            "cat": "Op",
            "tid": 0
        },
        {
            "pid": 1,
            "dur": 20409,
            "name": "_FusedConv2D",
            "ph": "X",
            "args": {
                "input2": "conv4/biases/read",
                "op": "_FusedConv2D",
                "input0": "conv3",
                "name": "conv4",
                "input1": "conv4/weights/read"
            },
            "ts": 1554448473141898,
            "cat": "Op",
            "tid": 0
        },
        {
            "pid": 1,
            "name": "conv4/weights/read",
            "ph": "s",
            "ts": 1554448472992543,
            "cat": "DataFlow",
            "tid": 1,
            "id": 20
        },
        {
            "pid": 1,
            "name": "conv4/weights/read",
            "ph": "t",
            "ts": 1554448473141898,
            "cat": "DataFlow",
            "tid": 0,
            "id": 20
        },
        {
            "pid": 1,
            "name": "conv4/biases/read",
            "ph": "s",
            "ts": 1554448472992610,
            "cat": "DataFlow",
            "tid": 2,
            "id": 21
        },
        {
            "pid": 1,
            "name": "conv4/biases/read",
            "ph": "t",
            "ts": 1554448473141898,
            "cat": "DataFlow",
            "tid": 0,
            "id": 21
        },
        {
            "pid": 1,
            "dur": 18,
            "name": "Const",
            "ph": "X",
            "args": {
                "op": "Const",
                "input0": "^conv5/weights/read",
                "name": "ConstantFolding/gradients/conv5/Conv2D_grad/ShapeN-matshapes-1",
                "input1": "^conv4"
            },
            "ts": 1554448473162338,
            "cat": "Op",
            "tid": 0
        },
        {
            "pid": 1,
            "dur": 3,
            "name": "Const",
            "ph": "X",
            "args": {
                "op": "Const",
                "input0": "^conv5/weights/read",
                "name": "ConstantFolding/gradients/conv5/Conv2D_grad/ShapeN-matshapes-0",
                "input1": "^conv4"
            },
            "ts": 1554448473162359,
            "cat": "Op",
            "tid": 0
        },
        {
            "pid": 1,
            "dur": 19642,
            "name": "_FusedConv2D",
            "ph": "X",
            "args": {
                "input2": "conv5/biases/read",
                "op": "_FusedConv2D",
                "input0": "conv4",
                "name": "conv5/Relu",
                "input1": "conv5/weights/read"
            },
            "ts": 1554448473162366,
            "cat": "Op",
            "tid": 0
        },
        {
            "pid": 1,
            "dur": 389,
            "name": "MaxPool",
            "ph": "X",
            "args": {
                "op": "MaxPool",
                "input0": "conv5/Relu",
                "name": "conv5/pool5"
            },
            "ts": 1554448473182027,
            "cat": "Op",
            "tid": 0
        },
        {
            "pid": 1,
            "dur": 8,
            "name": "Reshape",
            "ph": "X",
            "args": {
                "op": "Reshape",
                "input0": "conv5/pool5",
                "name": "Reshape",
                "input1": "Reshape/shape"
            },
            "ts": 1554448473182425,
            "cat": "Op",
            "tid": 0
        },
        {
            "pid": 1,
            "name": "Reshape/shape",
            "ph": "s",
            "ts": 1554448472992544,
            "cat": "DataFlow",
            "tid": 2,
            "id": 22
        },
        {
            "pid": 1,
            "name": "Reshape/shape",
            "ph": "t",
            "ts": 1554448473182425,
            "cat": "DataFlow",
            "tid": 0,
            "id": 22
        },
        {
            "pid": 1,
            "dur": 21780,
            "name": "MatMul",
            "ph": "X",
            "args": {
                "op": "MatMul",
                "input0": "Reshape",
                "name": "MatMul",
                "input1": "weight6/read"
            },
            "ts": 1554448473182436,
            "cat": "Op",
            "tid": 0
        },
        {
            "pid": 1,
            "dur": 172,
            "name": "Add",
            "ph": "X",
            "args": {
                "op": "Add",
                "input0": "MatMul",
                "name": "Add",
                "input1": "ful_bias1/read"
            },
            "ts": 1554448473204244,
            "cat": "Op",
            "tid": 0
        },
        {
            "pid": 1,
            "name": "ful_bias1/read",
            "ph": "s",
            "ts": 1554448472992551,
            "cat": "DataFlow",
            "tid": 2,
            "id": 23
        },
        {
            "pid": 1,
            "name": "ful_bias1/read",
            "ph": "t",
            "ts": 1554448473204244,
            "cat": "DataFlow",
            "tid": 0,
            "id": 23
        },
        {
            "pid": 1,
            "dur": 56,
            "name": "Relu",
            "ph": "X",
            "args": {
                "op": "Relu",
                "input0": "Add",
                "name": "Relu"
            },
            "ts": 1554448473204420,
            "cat": "Op",
            "tid": 0
        },
        {
            "pid": 1,
            "dur": 4469,
            "name": "MatMul",
            "ph": "X",
            "args": {
                "op": "MatMul",
                "input0": "Relu",
                "name": "MatMul_1",
                "input1": "weight7/read"
            },
            "ts": 1554448473204481,
            "cat": "Op",
            "tid": 0
        },
        {
            "pid": 1,
            "name": "weight7/read",
            "ph": "s",
            "ts": 1554448472992614,
            "cat": "DataFlow",
            "tid": 4,
            "id": 24
        },
        {
            "pid": 1,
            "name": "weight7/read",
            "ph": "t",
            "ts": 1554448473204481,
            "cat": "DataFlow",
            "tid": 0,
            "id": 24
        },
        {
            "pid": 1,
            "dur": 127,
            "name": "Add",
            "ph": "X",
            "args": {
                "op": "Add",
                "input0": "MatMul_1",
                "name": "Add_1",
                "input1": "ful_bias2/read"
            },
            "ts": 1554448473208972,
            "cat": "Op",
            "tid": 0
        },
        {
            "pid": 1,
            "dur": 50,
            "name": "Relu",
            "ph": "X",
            "args": {
                "op": "Relu",
                "input0": "Add_1",
                "name": "Relu_1"
            },
            "ts": 1554448473209105,
            "cat": "Op",
            "tid": 0
        },
        {
            "pid": 1,
            "dur": 1037,
            "name": "MatMul",
            "ph": "X",
            "args": {
                "op": "MatMul",
                "input0": "Relu_1",
                "name": "MatMul_2",
                "input1": "weight8/read"
            },
            "ts": 1554448473209157,
            "cat": "Op",
            "tid": 0
        },
        {
            "pid": 1,
            "name": "weight8/read",
            "ph": "s",
            "ts": 1554448472992586,
            "cat": "DataFlow",
            "tid": 1,
            "id": 25
        },
        {
            "pid": 1,
            "name": "weight8/read",
            "ph": "t",
            "ts": 1554448473209157,
            "cat": "DataFlow",
            "tid": 0,
            "id": 25
        },
        {
            "pid": 1,
            "dur": 42,
            "name": "Add",
            "ph": "X",
            "args": {
                "op": "Add",
                "input0": "MatMul_2",
                "name": "Add_2",
                "input1": "ful_bias3/read"
            },
            "ts": 1554448473210201,
            "cat": "Op",
            "tid": 0
        },
        {
            "pid": 1,
            "name": "ful_bias3/read",
            "ph": "s",
            "ts": 1554448472992572,
            "cat": "DataFlow",
            "tid": 1,
            "id": 26
        },
        {
            "pid": 1,
            "name": "ful_bias3/read",
            "ph": "t",
            "ts": 1554448473210201,
            "cat": "DataFlow",
            "tid": 0,
            "id": 26
        },
        {
            "pid": 1,
            "dur": 8,
            "name": "Relu",
            "ph": "X",
            "args": {
                "op": "Relu",
                "input0": "Add_2",
                "name": "Relu_2"
            },
            "ts": 1554448473210246,
            "cat": "Op",
            "tid": 0
        },
        {
            "pid": 1,
            "dur": 63,
            "name": "MatMul",
            "ph": "X",
            "args": {
                "op": "MatMul",
                "input0": "Relu_2",
                "name": "MatMul_3",
                "input1": "weight9/read"
            },
            "ts": 1554448473210255,
            "cat": "Op",
            "tid": 0
        },
        {
            "pid": 1,
            "dur": 13,
            "name": "Add",
            "ph": "X",
            "args": {
                "op": "Add",
                "input0": "MatMul_3",
                "name": "add_3",
                "input1": "bias9/read"
            },
            "ts": 1554448473210321,
            "cat": "Op",
            "tid": 0
        },
        {
            "pid": 1,
            "name": "bias9/read",
            "ph": "s",
            "ts": 1554448472992587,
            "cat": "DataFlow",
            "tid": 3,
            "id": 27
        },
        {
            "pid": 1,
            "name": "bias9/read",
            "ph": "t",
            "ts": 1554448473210321,
            "cat": "DataFlow",
            "tid": 0,
            "id": 27
        },
        {
            "pid": 1,
            "dur": 30,
            "name": "Softmax",
            "ph": "X",
            "args": {
                "op": "Softmax",
                "input0": "add_3",
                "name": "Softmax"
            },
            "ts": 1554448473210336,
            "cat": "Op",
            "tid": 0
        },
        {
            "pid": 1,
            "dur": 5,
            "name": "Square",
            "ph": "X",
            "args": {
                "op": "Square",
                "input0": "Softmax",
                "name": "gradients/Softmax_grad/ArithmeticOptimizer/ReplaceMulWithSquare_mul"
            },
            "ts": 1554448473210368,
            "cat": "Op",
            "tid": 0
        },
        {
            "pid": 1,
            "dur": 50,
            "name": "Sum",
            "ph": "X",
            "args": {
                "op": "Sum",
                "input0": "gradients/Softmax_grad/ArithmeticOptimizer/ReplaceMulWithSquare_mul",
                "name": "gradients/Softmax_grad/Sum",
                "input1": "gradients/Softmax_grad/Sum/reduction_indices"
            },
            "ts": 1554448473210375,
            "cat": "Op",
            "tid": 0
        },
        {
            "pid": 1,
            "name": "gradients/Softmax_grad/Sum/reduction_indices",
            "ph": "s",
            "ts": 1554448472992547,
            "cat": "DataFlow",
            "tid": 3,
            "id": 28
        },
        {
            "pid": 1,
            "name": "gradients/Softmax_grad/Sum/reduction_indices",
            "ph": "t",
            "ts": 1554448473210375,
            "cat": "DataFlow",
            "tid": 0,
            "id": 28
        },
        {
            "pid": 1,
            "dur": 1075,
            "name": "Sub",
            "ph": "X",
            "args": {
                "op": "Sub",
                "input0": "Softmax",
                "name": "gradients/Softmax_grad/sub",
                "input1": "gradients/Softmax_grad/Sum"
            },
            "ts": 1554448473210428,
            "cat": "Op",
            "tid": 0
        },
        {
            "pid": 1,
            "dur": 7,
            "name": "Mul",
            "ph": "X",
            "args": {
                "op": "Mul",
                "input0": "gradients/Softmax_grad/sub",
                "name": "gradients/Softmax_grad/mul_1",
                "input1": "Softmax"
            },
            "ts": 1554448473211507,
            "cat": "Op",
            "tid": 0
        },
        {
            "pid": 1,
            "dur": 55,
            "name": "MatMul",
            "ph": "X",
            "args": {
                "op": "MatMul",
                "input0": "gradients/Softmax_grad/mul_1",
                "name": "gradients/MatMul_3_grad/MatMul",
                "input1": "weight9/read"
            },
            "ts": 1554448473211516,
            "cat": "Op",
            "tid": 0
        },
        {
            "pid": 1,
            "dur": 72,
            "name": "ReluGrad",
            "ph": "X",
            "args": {
                "op": "ReluGrad",
                "input0": "gradients/MatMul_3_grad/MatMul",
                "name": "gradients/Relu_2_grad/ReluGrad",
                "input1": "Relu_2"
            },
            "ts": 1554448473211576,
            "cat": "Op",
            "tid": 0
        },
        {
            "pid": 1,
            "dur": 1252,
            "name": "MatMul",
            "ph": "X",
            "args": {
                "op": "MatMul",
                "input0": "gradients/Relu_2_grad/ReluGrad",
                "name": "gradients/MatMul_2_grad/MatMul",
                "input1": "weight8/read"
            },
            "ts": 1554448473211651,
            "cat": "Op",
            "tid": 0
        },
        {
            "pid": 1,
            "name": "weight8/read",
            "ph": "s",
            "ts": 1554448472992586,
            "cat": "DataFlow",
            "tid": 1,
            "id": 29
        },
        {
            "pid": 1,
            "name": "weight8/read",
            "ph": "t",
            "ts": 1554448473211651,
            "cat": "DataFlow",
            "tid": 0,
            "id": 29
        },
        {
            "pid": 1,
            "dur": 112,
            "name": "ReluGrad",
            "ph": "X",
            "args": {
                "op": "ReluGrad",
                "input0": "gradients/MatMul_2_grad/MatMul",
                "name": "gradients/Relu_1_grad/ReluGrad",
                "input1": "Relu_1"
            },
            "ts": 1554448473212912,
            "cat": "Op",
            "tid": 0
        },
        {
            "pid": 1,
            "dur": 4913,
            "name": "MatMul",
            "ph": "X",
            "args": {
                "op": "MatMul",
                "input0": "gradients/Relu_1_grad/ReluGrad",
                "name": "gradients/MatMul_1_grad/MatMul",
                "input1": "weight7/read"
            },
            "ts": 1554448473213028,
            "cat": "Op",
            "tid": 0
        },
        {
            "pid": 1,
            "name": "weight7/read",
            "ph": "s",
            "ts": 1554448472992614,
            "cat": "DataFlow",
            "tid": 4,
            "id": 30
        },
        {
            "pid": 1,
            "name": "weight7/read",
            "ph": "t",
            "ts": 1554448473213028,
            "cat": "DataFlow",
            "tid": 0,
            "id": 30
        },
        {
            "pid": 1,
            "dur": 123,
            "name": "ReluGrad",
            "ph": "X",
            "args": {
                "op": "ReluGrad",
                "input0": "gradients/MatMul_1_grad/MatMul",
                "name": "gradients/Relu_grad/ReluGrad",
                "input1": "Relu"
            },
            "ts": 1554448473217963,
            "cat": "Op",
            "tid": 0
        },
        {
            "pid": 1,
            "dur": 22333,
            "name": "MatMul",
            "ph": "X",
            "args": {
                "op": "MatMul",
                "input0": "gradients/Relu_grad/ReluGrad",
                "name": "gradients/MatMul_grad/MatMul",
                "input1": "weight6/read"
            },
            "ts": 1554448473218090,
            "cat": "Op",
            "tid": 0
        },
        {
            "pid": 1,
            "dur": 10,
            "name": "Reshape",
            "ph": "X",
            "args": {
                "op": "Reshape",
                "input0": "gradients/MatMul_grad/MatMul",
                "name": "gradients/Reshape_grad/Reshape",
                "input1": "gradients/Reshape_grad/Shape"
            },
            "ts": 1554448473240441,
            "cat": "Op",
            "tid": 0
        },
        {
            "pid": 1,
            "name": "gradients/Reshape_grad/Shape",
            "ph": "s",
            "ts": 1554448472992539,
            "cat": "DataFlow",
            "tid": 2,
            "id": 31
        },
        {
            "pid": 1,
            "name": "gradients/Reshape_grad/Shape",
            "ph": "t",
            "ts": 1554448473240441,
            "cat": "DataFlow",
            "tid": 0,
            "id": 31
        },
        {
            "pid": 1,
            "dur": 718,
            "name": "MaxPoolGrad",
            "ph": "X",
            "args": {
                "input2": "gradients/Reshape_grad/Reshape",
                "op": "MaxPoolGrad",
                "input0": "conv5/Relu",
                "name": "gradients/conv5/pool5_grad/MaxPoolGrad",
                "input1": "conv5/pool5"
            },
            "ts": 1554448473240454,
            "cat": "Op",
            "tid": 0
        },
        {
            "pid": 1,
            "dur": 268,
            "name": "ReluGrad",
            "ph": "X",
            "args": {
                "op": "ReluGrad",
                "input0": "gradients/conv5/pool5_grad/MaxPoolGrad",
                "name": "gradients/conv5/Relu_grad/ReluGrad",
                "input1": "conv5/Relu"
            },
            "ts": 1554448473241178,
            "cat": "Op",
            "tid": 0
        },
        {
            "pid": 1,
            "dur": 3,
            "name": "_Retval",
            "ph": "X",
            "args": {
                "op": "_Retval",
                "input0": "gradients/conv5/Relu_grad/ReluGrad",
                "name": "_retval_gradients/conv5/Relu_grad/ReluGrad_0_9"
            },
            "ts": 1554448473241458,
            "cat": "Op",
            "tid": 0
        },
        {
            "pid": 1,
            "dur": 30443,
            "name": "Conv2DBackpropFilter",
            "ph": "X",
            "args": {
                "input2": "gradients/conv5/Relu_grad/ReluGrad",
                "op": "Conv2DBackpropFilter",
                "input0": "conv4",
                "name": "gradients/conv5/Conv2D_grad/Conv2DBackpropFilter",
                "input1": "ConstantFolding/gradients/conv5/Conv2D_grad/ShapeN-matshapes-1"
            },
            "ts": 1554448473241468,
            "cat": "Op",
            "tid": 0
        },
        {
            "pid": 1,
            "dur": 5,
            "name": "_Retval",
            "ph": "X",
            "args": {
                "op": "_Retval",
                "input0": "gradients/conv5/Conv2D_grad/Conv2DBackpropFilter",
                "name": "_retval_gradients/conv5/Conv2D_grad/Conv2DBackpropFilter_0_8"
            },
            "ts": 1554448473271933,
            "cat": "Op",
            "tid": 0
        },
        {
            "pid": 1,
            "dur": 35766,
            "name": "Conv2DBackpropInput",
            "ph": "X",
            "args": {
                "input2": "gradients/conv5/Relu_grad/ReluGrad",
                "op": "Conv2DBackpropInput",
                "input0": "ConstantFolding/gradients/conv5/Conv2D_grad/ShapeN-matshapes-0",
                "name": "gradients/conv5/Conv2D_grad/Conv2DBackpropInput",
                "input1": "conv5/weights/read"
            },
            "ts": 1554448473241464,
            "cat": "Op",
            "tid": 1
        },
        {
            "pid": 1,
            "name": "ConstantFolding/gradients/conv5/Conv2D_grad/ShapeN-matshapes-0",
            "ph": "s",
            "ts": 1554448473162362,
            "cat": "DataFlow",
            "tid": 0,
            "id": 32
        },
        {
            "pid": 1,
            "name": "ConstantFolding/gradients/conv5/Conv2D_grad/ShapeN-matshapes-0",
            "ph": "t",
            "ts": 1554448473241464,
            "cat": "DataFlow",
            "tid": 1,
            "id": 32
        },
        {
            "pid": 1,
            "name": "conv5/weights/read",
            "ph": "s",
            "ts": 1554448472992532,
            "cat": "DataFlow",
            "tid": 0,
            "id": 33
        },
        {
            "pid": 1,
            "name": "conv5/weights/read",
            "ph": "t",
            "ts": 1554448473241464,
            "cat": "DataFlow",
            "tid": 1,
            "id": 33
        },
        {
            "pid": 1,
            "name": "gradients/conv5/Relu_grad/ReluGrad",
            "ph": "s",
            "ts": 1554448473241446,
            "cat": "DataFlow",
            "tid": 0,
            "id": 34
        },
        {
            "pid": 1,
            "name": "gradients/conv5/Relu_grad/ReluGrad",
            "ph": "t",
            "ts": 1554448473241464,
            "cat": "DataFlow",
            "tid": 1,
            "id": 34
        },
        {
            "pid": 1,
            "dur": 438,
            "name": "ReluGrad",
            "ph": "X",
            "args": {
                "op": "ReluGrad",
                "input0": "gradients/conv5/Conv2D_grad/Conv2DBackpropInput",
                "name": "gradients/conv4_grad/ReluGrad",
                "input1": "conv4"
            },
            "ts": 1554448473277239,
            "cat": "Op",
            "tid": 0
        },
        {
            "pid": 1,
            "name": "gradients/conv5/Conv2D_grad/Conv2DBackpropInput",
            "ph": "s",
            "ts": 1554448473277230,
            "cat": "DataFlow",
            "tid": 1,
            "id": 35
        },
        {
            "pid": 1,
            "name": "gradients/conv5/Conv2D_grad/Conv2DBackpropInput",
            "ph": "t",
            "ts": 1554448473277239,
            "cat": "DataFlow",
            "tid": 0,
            "id": 35
        },
        {
            "pid": 1,
            "dur": 899,
            "name": "BiasAddGrad",
            "ph": "X",
            "args": {
                "op": "BiasAddGrad",
                "input0": "gradients/conv4_grad/ReluGrad",
                "name": "gradients/conv4/BiasAdd_grad/BiasAddGrad"
            },
            "ts": 1554448473277773,
            "cat": "Op",
            "tid": 0
        },
        {
            "pid": 1,
            "dur": 2,
            "name": "_Retval",
            "ph": "X",
            "args": {
                "op": "_Retval",
                "input0": "gradients/conv4/BiasAdd_grad/BiasAddGrad",
                "name": "_retval_gradients/conv4/BiasAdd_grad/BiasAddGrad_0_6"
            },
            "ts": 1554448473278677,
            "cat": "Op",
            "tid": 0
        },
        {
            "pid": 1,
            "dur": 40457,
            "name": "Conv2DBackpropFilter",
            "ph": "X",
            "args": {
                "input2": "gradients/conv4_grad/ReluGrad",
                "op": "Conv2DBackpropFilter",
                "input0": "conv3",
                "name": "gradients/conv4/Conv2D_grad/Conv2DBackpropFilter",
                "input1": "ConstantFolding/gradients/conv4/Conv2D_grad/ShapeN-matshapes-1"
            },
            "ts": 1554448473277762,
            "cat": "Op",
            "tid": 1
        },
        {
            "pid": 1,
            "name": "conv3",
            "ph": "s",
            "ts": 1554448473141860,
            "cat": "DataFlow",
            "tid": 0,
            "id": 36
        },
        {
            "pid": 1,
            "name": "conv3",
            "ph": "t",
            "ts": 1554448473277762,
            "cat": "DataFlow",
            "tid": 1,
            "id": 36
        },
        {
            "pid": 1,
            "name": "ConstantFolding/gradients/conv4/Conv2D_grad/ShapeN-matshapes-1",
            "ph": "s",
            "ts": 1554448473141887,
            "cat": "DataFlow",
            "tid": 0,
            "id": 37
        },
        {
            "pid": 1,
            "name": "ConstantFolding/gradients/conv4/Conv2D_grad/ShapeN-matshapes-1",
            "ph": "t",
            "ts": 1554448473277762,
            "cat": "DataFlow",
            "tid": 1,
            "id": 37
        },
        {
            "pid": 1,
            "name": "gradients/conv4_grad/ReluGrad",
            "ph": "s",
            "ts": 1554448473277677,
            "cat": "DataFlow",
            "tid": 0,
            "id": 38
        },
        {
            "pid": 1,
            "name": "gradients/conv4_grad/ReluGrad",
            "ph": "t",
            "ts": 1554448473277762,
            "cat": "DataFlow",
            "tid": 1,
            "id": 38
        },
        {
            "pid": 1,
            "dur": 7,
            "name": "_Retval",
            "ph": "X",
            "args": {
                "op": "_Retval",
                "input0": "gradients/conv4/Conv2D_grad/Conv2DBackpropFilter",
                "name": "_retval_gradients/conv4/Conv2D_grad/Conv2DBackpropFilter_0_7"
            },
            "ts": 1554448473318247,
            "cat": "Op",
            "tid": 0
        },
        {
            "pid": 1,
            "name": "gradients/conv4/Conv2D_grad/Conv2DBackpropFilter",
            "ph": "s",
            "ts": 1554448473318219,
            "cat": "DataFlow",
            "tid": 1,
            "id": 39
        },
        {
            "pid": 1,
            "name": "gradients/conv4/Conv2D_grad/Conv2DBackpropFilter",
            "ph": "t",
            "ts": 1554448473318247,
            "cat": "DataFlow",
            "tid": 0,
            "id": 39
        },
        {
            "pid": 1,
            "dur": 95987,
            "name": "Conv2DBackpropInput",
            "ph": "X",
            "args": {
                "input2": "gradients/conv4_grad/ReluGrad",
                "op": "Conv2DBackpropInput",
                "input0": "ConstantFolding/gradients/conv4/Conv2D_grad/ShapeN-matshapes-0",
                "name": "gradients/conv4/Conv2D_grad/Conv2DBackpropInput",
                "input1": "conv4/weights/read"
            },
            "ts": 1554448473277718,
            "cat": "Op",
            "tid": 2
        },
        {
            "pid": 1,
            "name": "ConstantFolding/gradients/conv4/Conv2D_grad/ShapeN-matshapes-0",
            "ph": "s",
            "ts": 1554448473141895,
            "cat": "DataFlow",
            "tid": 0,
            "id": 40
        },
        {
            "pid": 1,
            "name": "ConstantFolding/gradients/conv4/Conv2D_grad/ShapeN-matshapes-0",
            "ph": "t",
            "ts": 1554448473277718,
            "cat": "DataFlow",
            "tid": 2,
            "id": 40
        },
        {
            "pid": 1,
            "name": "conv4/weights/read",
            "ph": "s",
            "ts": 1554448472992543,
            "cat": "DataFlow",
            "tid": 1,
            "id": 41
        },
        {
            "pid": 1,
            "name": "conv4/weights/read",
            "ph": "t",
            "ts": 1554448473277718,
            "cat": "DataFlow",
            "tid": 2,
            "id": 41
        },
        {
            "pid": 1,
            "name": "gradients/conv4_grad/ReluGrad",
            "ph": "s",
            "ts": 1554448473277677,
            "cat": "DataFlow",
            "tid": 0,
            "id": 42
        },
        {
            "pid": 1,
            "name": "gradients/conv4_grad/ReluGrad",
            "ph": "t",
            "ts": 1554448473277718,
            "cat": "DataFlow",
            "tid": 2,
            "id": 42
        },
        {
            "pid": 1,
            "dur": 650,
            "name": "ReluGrad",
            "ph": "X",
            "args": {
                "op": "ReluGrad",
                "input0": "gradients/conv4/Conv2D_grad/Conv2DBackpropInput",
                "name": "gradients/conv3_grad/ReluGrad",
                "input1": "conv3"
            },
            "ts": 1554448473373722,
            "cat": "Op",
            "tid": 0
        },
        {
            "pid": 1,
            "name": "gradients/conv4/Conv2D_grad/Conv2DBackpropInput",
            "ph": "s",
            "ts": 1554448473373705,
            "cat": "DataFlow",
            "tid": 2,
            "id": 43
        },
        {
            "pid": 1,
            "name": "gradients/conv4/Conv2D_grad/Conv2DBackpropInput",
            "ph": "t",
            "ts": 1554448473373722,
            "cat": "DataFlow",
            "tid": 0,
            "id": 43
        },
        {
            "pid": 1,
            "dur": 1309,
            "name": "BiasAddGrad",
            "ph": "X",
            "args": {
                "op": "BiasAddGrad",
                "input0": "gradients/conv3_grad/ReluGrad",
                "name": "gradients/conv3/BiasAdd_grad/BiasAddGrad"
            },
            "ts": 1554448473374446,
            "cat": "Op",
            "tid": 0
        },
        {
            "pid": 1,
            "dur": 4,
            "name": "_Retval",
            "ph": "X",
            "args": {
                "op": "_Retval",
                "input0": "gradients/conv3/BiasAdd_grad/BiasAddGrad",
                "name": "_retval_gradients/conv3/BiasAdd_grad/BiasAddGrad_0_4"
            },
            "ts": 1554448473375763,
            "cat": "Op",
            "tid": 0
        },
        {
            "pid": 1,
            "dur": 33898,
            "name": "Conv2DBackpropFilter",
            "ph": "X",
            "args": {
                "input2": "gradients/conv3_grad/ReluGrad",
                "op": "Conv2DBackpropFilter",
                "input0": "conv2/pool2",
                "name": "gradients/conv3/Conv2D_grad/Conv2DBackpropFilter",
                "input1": "ConstantFolding/gradients/conv3/Conv2D_grad/ShapeN-matshapes-1"
            },
            "ts": 1554448473374444,
            "cat": "Op",
            "tid": 1
        },
        {
            "pid": 1,
            "name": "conv2/pool2",
            "ph": "s",
            "ts": 1554448473117190,
            "cat": "DataFlow",
            "tid": 0,
            "id": 44
        },
        {
            "pid": 1,
            "name": "conv2/pool2",
            "ph": "t",
            "ts": 1554448473374444,
            "cat": "DataFlow",
            "tid": 1,
            "id": 44
        },
        {
            "pid": 1,
            "name": "ConstantFolding/gradients/conv3/Conv2D_grad/ShapeN-matshapes-1",
            "ph": "s",
            "ts": 1554448473117211,
            "cat": "DataFlow",
            "tid": 0,
            "id": 45
        },
        {
            "pid": 1,
            "name": "ConstantFolding/gradients/conv3/Conv2D_grad/ShapeN-matshapes-1",
            "ph": "t",
            "ts": 1554448473374444,
            "cat": "DataFlow",
            "tid": 1,
            "id": 45
        },
        {
            "pid": 1,
            "name": "gradients/conv3_grad/ReluGrad",
            "ph": "s",
            "ts": 1554448473374372,
            "cat": "DataFlow",
            "tid": 0,
            "id": 46
        },
        {
            "pid": 1,
            "name": "gradients/conv3_grad/ReluGrad",
            "ph": "t",
            "ts": 1554448473374444,
            "cat": "DataFlow",
            "tid": 1,
            "id": 46
        },
        {
            "pid": 1,
            "dur": 6,
            "name": "_Retval",
            "ph": "X",
            "args": {
                "op": "_Retval",
                "input0": "gradients/conv3/Conv2D_grad/Conv2DBackpropFilter",
                "name": "_retval_gradients/conv3/Conv2D_grad/Conv2DBackpropFilter_0_5"
            },
            "ts": 1554448473408371,
            "cat": "Op",
            "tid": 0
        },
        {
            "pid": 1,
            "name": "gradients/conv3/Conv2D_grad/Conv2DBackpropFilter",
            "ph": "s",
            "ts": 1554448473408342,
            "cat": "DataFlow",
            "tid": 1,
            "id": 47
        },
        {
            "pid": 1,
            "name": "gradients/conv3/Conv2D_grad/Conv2DBackpropFilter",
            "ph": "t",
            "ts": 1554448473408371,
            "cat": "DataFlow",
            "tid": 0,
            "id": 47
        },
        {
            "pid": 1,
            "dur": 51208,
            "name": "Conv2DBackpropInput",
            "ph": "X",
            "args": {
                "input2": "gradients/conv3_grad/ReluGrad",
                "op": "Conv2DBackpropInput",
                "input0": "ConstantFolding/gradients/conv3/Conv2D_grad/ShapeN-matshapes-0",
                "name": "gradients/conv3/Conv2D_grad/Conv2DBackpropInput",
                "input1": "conv3/weights/read"
            },
            "ts": 1554448473374411,
            "cat": "Op",
            "tid": 2
        },
        {
            "pid": 1,
            "name": "ConstantFolding/gradients/conv3/Conv2D_grad/ShapeN-matshapes-0",
            "ph": "s",
            "ts": 1554448473117217,
            "cat": "DataFlow",
            "tid": 0,
            "id": 48
        },
        {
            "pid": 1,
            "name": "ConstantFolding/gradients/conv3/Conv2D_grad/ShapeN-matshapes-0",
            "ph": "t",
            "ts": 1554448473374411,
            "cat": "DataFlow",
            "tid": 2,
            "id": 48
        },
        {
            "pid": 1,
            "name": "conv3/weights/read",
            "ph": "s",
            "ts": 1554448472992546,
            "cat": "DataFlow",
            "tid": 4,
            "id": 49
        },
        {
            "pid": 1,
            "name": "conv3/weights/read",
            "ph": "t",
            "ts": 1554448473374411,
            "cat": "DataFlow",
            "tid": 2,
            "id": 49
        },
        {
            "pid": 1,
            "name": "gradients/conv3_grad/ReluGrad",
            "ph": "s",
            "ts": 1554448473374372,
            "cat": "DataFlow",
            "tid": 0,
            "id": 50
        },
        {
            "pid": 1,
            "name": "gradients/conv3_grad/ReluGrad",
            "ph": "t",
            "ts": 1554448473374411,
            "cat": "DataFlow",
            "tid": 2,
            "id": 50
        },
        {
            "pid": 1,
            "dur": 3853,
            "name": "MaxPoolGrad",
            "ph": "X",
            "args": {
                "input2": "gradients/conv3/Conv2D_grad/Conv2DBackpropInput",
                "op": "MaxPoolGrad",
                "input0": "conv2/lrn2",
                "name": "gradients/conv2/pool2_grad/MaxPoolGrad",
                "input1": "conv2/pool2"
            },
            "ts": 1554448473425642,
            "cat": "Op",
            "tid": 0
        },
        {
            "pid": 1,
            "name": "gradients/conv3/Conv2D_grad/Conv2DBackpropInput",
            "ph": "s",
            "ts": 1554448473425619,
            "cat": "DataFlow",
            "tid": 2,
            "id": 51
        },
        {
            "pid": 1,
            "name": "gradients/conv3/Conv2D_grad/Conv2DBackpropInput",
            "ph": "t",
            "ts": 1554448473425642,
            "cat": "DataFlow",
            "tid": 0,
            "id": 51
        },
        {
            "pid": 1,
            "dur": 87448,
            "name": "LRNGrad",
            "ph": "X",
            "args": {
                "input2": "conv2/lrn2",
                "op": "LRNGrad",
                "input0": "gradients/conv2/pool2_grad/MaxPoolGrad",
                "name": "gradients/conv2/lrn2_grad/LRNGrad",
                "input1": "conv2"
            },
            "ts": 1554448473429522,
            "cat": "Op",
            "tid": 0
        },
        {
            "pid": 1,
            "dur": 991,
            "name": "ReluGrad",
            "ph": "X",
            "args": {
                "op": "ReluGrad",
                "input0": "gradients/conv2/lrn2_grad/LRNGrad",
                "name": "gradients/conv2_grad/ReluGrad",
                "input1": "conv2"
            },
            "ts": 1554448473516993,
            "cat": "Op",
            "tid": 0
        },
        {
            "pid": 1,
            "dur": 1766,
            "name": "BiasAddGrad",
            "ph": "X",
            "args": {
                "op": "BiasAddGrad",
                "input0": "gradients/conv2_grad/ReluGrad",
                "name": "gradients/conv2/BiasAdd_grad/BiasAddGrad"
            },
            "ts": 1554448473518034,
            "cat": "Op",
            "tid": 0
        },
        {
            "pid": 1,
            "dur": 4,
            "name": "_Retval",
            "ph": "X",
            "args": {
                "op": "_Retval",
                "input0": "gradients/conv2/BiasAdd_grad/BiasAddGrad",
                "name": "_retval_gradients/conv2/BiasAdd_grad/BiasAddGrad_0_2"
            },
            "ts": 1554448473519809,
            "cat": "Op",
            "tid": 0
        },
        {
            "pid": 1,
            "dur": 59475,
            "name": "Conv2DBackpropFilter",
            "ph": "X",
            "args": {
                "input2": "gradients/conv2_grad/ReluGrad",
                "op": "Conv2DBackpropFilter",
                "input0": "conv1/pool1",
                "name": "gradients/conv2/Conv2D_grad/Conv2DBackpropFilter",
                "input1": "ConstantFolding/gradients/conv2/Conv2D_grad/ShapeN-matshapes-1"
            },
            "ts": 1554448473518019,
            "cat": "Op",
            "tid": 1
        },
        {
            "pid": 1,
            "name": "conv1/pool1",
            "ph": "s",
            "ts": 1554448473066371,
            "cat": "DataFlow",
            "tid": 0,
            "id": 52
        },
        {
            "pid": 1,
            "name": "conv1/pool1",
            "ph": "t",
            "ts": 1554448473518019,
            "cat": "DataFlow",
            "tid": 1,
            "id": 52
        },
        {
            "pid": 1,
            "name": "ConstantFolding/gradients/conv2/Conv2D_grad/ShapeN-matshapes-1",
            "ph": "s",
            "ts": 1554448473066408,
            "cat": "DataFlow",
            "tid": 0,
            "id": 53
        },
        {
            "pid": 1,
            "name": "ConstantFolding/gradients/conv2/Conv2D_grad/ShapeN-matshapes-1",
            "ph": "t",
            "ts": 1554448473518019,
            "cat": "DataFlow",
            "tid": 1,
            "id": 53
        },
        {
            "pid": 1,
            "name": "gradients/conv2_grad/ReluGrad",
            "ph": "s",
            "ts": 1554448473517984,
            "cat": "DataFlow",
            "tid": 0,
            "id": 54
        },
        {
            "pid": 1,
            "name": "gradients/conv2_grad/ReluGrad",
            "ph": "t",
            "ts": 1554448473518019,
            "cat": "DataFlow",
            "tid": 1,
            "id": 54
        },
        {
            "pid": 1,
            "dur": 5,
            "name": "_Retval",
            "ph": "X",
            "args": {
                "op": "_Retval",
                "input0": "gradients/conv2/Conv2D_grad/Conv2DBackpropFilter",
                "name": "_retval_gradients/conv2/Conv2D_grad/Conv2DBackpropFilter_0_3"
            },
            "ts": 1554448473577541,
            "cat": "Op",
            "tid": 0
        },
        {
            "pid": 1,
            "name": "gradients/conv2/Conv2D_grad/Conv2DBackpropFilter",
            "ph": "s",
            "ts": 1554448473577494,
            "cat": "DataFlow",
            "tid": 1,
            "id": 55
        },
        {
            "pid": 1,
            "name": "gradients/conv2/Conv2D_grad/Conv2DBackpropFilter",
            "ph": "t",
            "ts": 1554448473577541,
            "cat": "DataFlow",
            "tid": 0,
            "id": 55
        },
        {
            "pid": 1,
            "dur": 85227,
            "name": "Conv2DBackpropInput",
            "ph": "X",
            "args": {
                "input2": "gradients/conv2_grad/ReluGrad",
                "op": "Conv2DBackpropInput",
                "input0": "ConstantFolding/gradients/conv2/Conv2D_grad/ShapeN-matshapes-0",
                "name": "gradients/conv2/Conv2D_grad/Conv2DBackpropInput",
                "input1": "conv2/weights/read"
            },
            "ts": 1554448473518002,
            "cat": "Op",
            "tid": 2
        },
        {
            "pid": 1,
            "name": "ConstantFolding/gradients/conv2/Conv2D_grad/ShapeN-matshapes-0",
            "ph": "s",
            "ts": 1554448473066415,
            "cat": "DataFlow",
            "tid": 0,
            "id": 56
        },
        {
            "pid": 1,
            "name": "ConstantFolding/gradients/conv2/Conv2D_grad/ShapeN-matshapes-0",
            "ph": "t",
            "ts": 1554448473518002,
            "cat": "DataFlow",
            "tid": 2,
            "id": 56
        },
        {
            "pid": 1,
            "name": "conv2/weights/read",
            "ph": "s",
            "ts": 1554448472992559,
            "cat": "DataFlow",
            "tid": 1,
            "id": 57
        },
        {
            "pid": 1,
            "name": "conv2/weights/read",
            "ph": "t",
            "ts": 1554448473518002,
            "cat": "DataFlow",
            "tid": 2,
            "id": 57
        },
        {
            "pid": 1,
            "name": "gradients/conv2_grad/ReluGrad",
            "ph": "s",
            "ts": 1554448473517984,
            "cat": "DataFlow",
            "tid": 0,
            "id": 58
        },
        {
            "pid": 1,
            "name": "gradients/conv2_grad/ReluGrad",
            "ph": "t",
            "ts": 1554448473518002,
            "cat": "DataFlow",
            "tid": 2,
            "id": 58
        },
        {
            "pid": 1,
            "dur": 5321,
            "name": "MaxPoolGrad",
            "ph": "X",
            "args": {
                "input2": "gradients/conv2/Conv2D_grad/Conv2DBackpropInput",
                "op": "MaxPoolGrad",
                "input0": "conv1/lrn1",
                "name": "gradients/conv1/pool1_grad/MaxPoolGrad",
                "input1": "conv1/pool1"
            },
            "ts": 1554448473603248,
            "cat": "Op",
            "tid": 0
        },
        {
            "pid": 1,
            "name": "gradients/conv2/Conv2D_grad/Conv2DBackpropInput",
            "ph": "s",
            "ts": 1554448473603229,
            "cat": "DataFlow",
            "tid": 2,
            "id": 59
        },
        {
            "pid": 1,
            "name": "gradients/conv2/Conv2D_grad/Conv2DBackpropInput",
            "ph": "t",
            "ts": 1554448473603248,
            "cat": "DataFlow",
            "tid": 0,
            "id": 59
        },
        {
            "pid": 1,
            "dur": 65517,
            "name": "LRNGrad",
            "ph": "X",
            "args": {
                "input2": "conv1/lrn1",
                "op": "LRNGrad",
                "input0": "gradients/conv1/pool1_grad/MaxPoolGrad",
                "name": "gradients/conv1/lrn1_grad/LRNGrad",
                "input1": "conv1"
            },
            "ts": 1554448473608594,
            "cat": "Op",
            "tid": 0
        },
        {
            "pid": 1,
            "dur": 1928,
            "name": "ReluGrad",
            "ph": "X",
            "args": {
                "op": "ReluGrad",
                "input0": "gradients/conv1/lrn1_grad/LRNGrad",
                "name": "gradients/conv1_grad/ReluGrad",
                "input1": "conv1"
            },
            "ts": 1554448473674140,
            "cat": "Op",
            "tid": 0
        },
        {
            "pid": 1,
            "dur": 5006,
            "name": "BiasAddGrad",
            "ph": "X",
            "args": {
                "op": "BiasAddGrad",
                "input0": "gradients/conv1_grad/ReluGrad",
                "name": "gradients/conv1/BiasAdd_grad/BiasAddGrad"
            },
            "ts": 1554448473676126,
            "cat": "Op",
            "tid": 0
        },
        {
            "pid": 1,
            "dur": 9,
            "name": "_Retval",
            "ph": "X",
            "args": {
                "op": "_Retval",
                "input0": "gradients/conv1/BiasAdd_grad/BiasAddGrad",
                "name": "_retval_gradients/conv1/BiasAdd_grad/BiasAddGrad_0_0"
            },
            "ts": 1554448473681150,
            "cat": "Op",
            "tid": 0
        },
        {
            "pid": 1,
            "dur": 49742,
            "name": "Conv2DBackpropFilter",
            "ph": "X",
            "args": {
                "input2": "gradients/conv1_grad/ReluGrad",
                "op": "Conv2DBackpropFilter",
                "input0": "Variable/read",
                "name": "gradients/conv1/Conv2D_grad/Conv2DBackpropFilter",
                "input1": "ConstantFolding/gradients/conv1/Conv2D_grad/ShapeN-matshapes-1"
            },
            "ts": 1554448473676086,
            "cat": "Op",
            "tid": 1
        },
        {
            "pid": 1,
            "name": "Variable/read",
            "ph": "s",
            "ts": 1554448472992565,
            "cat": "DataFlow",
            "tid": 0,
            "id": 60
        },
        {
            "pid": 1,
            "name": "Variable/read",
            "ph": "t",
            "ts": 1554448473676086,
            "cat": "DataFlow",
            "tid": 1,
            "id": 60
        },
        {
            "pid": 1,
            "name": "ConstantFolding/gradients/conv1/Conv2D_grad/ShapeN-matshapes-1",
            "ph": "s",
            "ts": 1554448472992599,
            "cat": "DataFlow",
            "tid": 0,
            "id": 61
        },
        {
            "pid": 1,
            "name": "ConstantFolding/gradients/conv1/Conv2D_grad/ShapeN-matshapes-1",
            "ph": "t",
            "ts": 1554448473676086,
            "cat": "DataFlow",
            "tid": 1,
            "id": 61
        },
        {
            "pid": 1,
            "name": "gradients/conv1_grad/ReluGrad",
            "ph": "s",
            "ts": 1554448473676068,
            "cat": "DataFlow",
            "tid": 0,
            "id": 62
        },
        {
            "pid": 1,
            "name": "gradients/conv1_grad/ReluGrad",
            "ph": "t",
            "ts": 1554448473676086,
            "cat": "DataFlow",
            "tid": 1,
            "id": 62
        },
        {
            "pid": 1,
            "dur": 11,
            "name": "_Retval",
            "ph": "X",
            "args": {
                "op": "_Retval",
                "input0": "gradients/conv1/Conv2D_grad/Conv2DBackpropFilter",
                "name": "_retval_gradients/conv1/Conv2D_grad/Conv2DBackpropFilter_0_1"
            },
            "ts": 1554448473725853,
            "cat": "Op",
            "tid": 0
        },
        {
            "pid": 1,
            "name": "gradients/conv1/Conv2D_grad/Conv2DBackpropFilter",
            "ph": "s",
            "ts": 1554448473725828,
            "cat": "DataFlow",
            "tid": 1,
            "id": 63
        },
        {
            "pid": 1,
            "name": "gradients/conv1/Conv2D_grad/Conv2DBackpropFilter",
            "ph": "t",
            "ts": 1554448473725853,
            "cat": "DataFlow",
            "tid": 0,
            "id": 63
        }
    ]
}